metacoder/__init__.py
metacoder/configuration.py
metacoder/metacoder.py
metacoder/registry.py
metacoder/coders/base_coder.py
metacoder/coders/claude.py
metacoder/coders/codex.py
metacoder/coders/dummy.py
metacoder/coders/gemini.py
metacoder/coders/goose.py
metacoder/coders/qwen.py
metacoder/evals/__init__.py
metacoder/evals/eval_model.py
metacoder/evals/runner.py
metacoder/mcps/__init__.py
metacoder/mcps/demo_lookup.py
metacoder/mcps/registry/basics.yaml
metacoder/mcps/registry/ontology.yaml
metacoder/mcps/registry/scilit.yaml
metacoder-0.1.0.dist-info/METADATA
metacoder-0.1.0.dist-info/WHEEL
metacoder-0.1.0.dist-info/entry_points.txt
metacoder-0.1.0.dist-info/RECORD
