Metadata-Version: 2.4
Name: metacoder
Version: 0.1.0
Summary: Add your description here
Author-email: Chris Mungall <cjm@berkeleybop.org>
Requires-Python: >=3.10
Requires-Dist: click>=8.1.8
Requires-Dist: deepeval>=3.3.4
Requires-Dist: evaluate>=0.4.5
Requires-Dist: fastmcp>=2.11.0
Requires-Dist: pydantic>=2.11.7
Requires-Dist: pyyaml>=6.0.2
Requires-Dist: ragas>=0.3.0
Requires-Dist: rouge-score>=0.1.2
